hello_labdata_ls/__init__.py
hello_labdata_ls/_modidx.py
hello_labdata_ls/core.py
hello_labdata_ls/greetings.py
hello_labdata_ls/jokes.py
hello_labdata_ls-0.0.5.dist-info/LICENSE
hello_labdata_ls-0.0.5.dist-info/METADATA
hello_labdata_ls-0.0.5.dist-info/WHEEL
hello_labdata_ls-0.0.5.dist-info/entry_points.txt
hello_labdata_ls-0.0.5.dist-info/top_level.txt
hello_labdata_ls-0.0.5.dist-info/RECORD
